[
  {
    "nurse_id": "N001",
    "name": "Lisa Ali",
    "skills": [
      "General",
      "OT",
      "Pediatrics",
      "ER"
    ],
    "certifications": [
      "BLS",
      "PALS",
      "ENPC"
    ],
    "experience_years": 10,
    "unavailability": [],
    "leave": {
      "annual": [],
      "sick": [],
      "maternity": []
    },
    "preferences": [
      "Morning"
    ],
    "contracted_hours": 44,
    "seniority_level": "Senior",
    "union_terms": [
      "max_45h_week",
      "1_rest_day"
    ]
  },
  {
    "nurse_id": "N002",
    "name": "Robert Jackson",
    "skills": [
      "General",
      "ICU",
      "Pediatrics",
      "OT",
      "ER"
    ],
    "certifications": [
      "BLS",
      "ENPC",
      "NRP"
    ],
    "experience_years": 7,
    "unavailability": [],
    "leave": {
      "annual": [],
      "sick": [],
      "maternity": []
    },
    "preferences": [
      "Morning"
    ],
    "contracted_hours": 44,
    "seniority_level": "Senior",
    "union_terms": [
      "max_45h_week",
      "1_rest_day"
    ]
  },
  {
    "nurse_id": "N003",
    "name": "Robert Rodriguez",
    "skills": [
      "General",
      "Pediatrics",
      "ER"
    ],
    "certifications": [
      "BLS"
    ],
    "experience_years": 14,
    "unavailability": [],
    "leave": {
      "annual": [],
      "sick": [],
      "maternity": []
    },
    "preferences": [
      "Evening"
    ],
    "contracted_hours": 44,
    "seniority_level": "Senior",
    "union_terms": [
      "max_45h_week",
      "1_rest_day"
    ]
  },
  {
    "nurse_id": "N004",
    "name": "Chloe Anderson",
    "skills": [
      "General",
      "ER",
      "ICU",
      "OT",
      "Pediatrics"
    ],
    "certifications": [
      "BLS",
      "CEN",
      "NRP"
    ],
    "experience_years": 1,
    "unavailability": [],
    "leave": {
      "annual": [],
      "sick": [],
      "maternity": []
    },
    "preferences": [
      "Morning"
    ],
    "contracted_hours": 36,
    "seniority_level": "Junior",
    "union_terms": [
      "max_45h_week",
      "1_rest_day"
    ]
  },
  {
    "nurse_id": "N005",
    "name": "Hassan Martinez",
    "skills": [
      "General",
      "OT",
      "ICU"
    ],
    "certifications": [
      "BLS",
      "CEN"
    ],
    "experience_years": 14,
    "unavailability": [],
    "leave": {
      "annual": [],
      "sick": [],
      "maternity": []
    },
    "preferences": [
      "Night"
    ],
    "contracted_hours": 44,
    "seniority_level": "Senior",
    "union_terms": [
      "max_45h_week",
      "1_rest_day"
    ]
  },
  {
    "nurse_id": "N006",
    "name": "Emily Clark",
    "skills": [
      "General",
      "Pediatrics",
      "ICU",
      "OT"
    ],
    "certifications": [
      "BLS",
      "NRP",
      "ENPC"
    ],
    "experience_years": 8,
    "unavailability": [],
    "leave": {
      "annual": [],
      "sick": [],
      "maternity": []
    },
    "preferences": [
      "Morning"
    ],
    "contracted_hours": 44,
    "seniority_level": "Senior",
    "union_terms": [
      "max_45h_week",
      "1_rest_day"
    ]
  },
  {
    "nurse_id": "N007",
    "name": "Ethan Lee",
    "skills": [
      "General",
      "ER",
      "OT",
      "ICU",
      "Pediatrics"
    ],
    "certifications": [
      "BLS"
    ],
    "experience_years": 5,
    "unavailability": [],
    "leave": {
      "annual": [],
      "sick": [],
      "maternity": []
    },
    "preferences": [
      "Night"
    ],
    "contracted_hours": 44,
    "seniority_level": "Senior",
    "union_terms": [
      "max_45h_week",
      "1_rest_day"
    ]
  },
  {
    "nurse_id": "N008",
    "name": "Carlos Santos",
    "skills": [
      "General",
      "ER",
      "Pediatrics",
      "ICU",
      "OT"
    ],
    "certifications": [
      "BLS"
    ],
    "experience_years": 2,
    "unavailability": [],
    "leave": {
      "annual": [],
      "sick": [],
      "maternity": []
    },
    "preferences": [
      "Evening"
    ],
    "contracted_hours": 40,
    "seniority_level": "Mid",
    "union_terms": [
      "max_45h_week",
      "1_rest_day"
    ]
  },
  {
    "nurse_id": "N009",
    "name": "Fatou Tan",
    "skills": [
      "General",
      "Pediatrics",
      "OT",
      "ICU",
      "ER"
    ],
    "certifications": [
      "BLS",
      "CEN"
    ],
    "experience_years": 6,
    "unavailability": [],
    "leave": {
      "annual": [],
      "sick": [],
      "maternity": []
    },
    "preferences": [
      "Night"
    ],
    "contracted_hours": 44,
    "seniority_level": "Senior",
    "union_terms": [
      "max_45h_week",
      "1_rest_day"
    ]
  },
  {
    "nurse_id": "N010",
    "name": "Sarah Lee",
    "skills": [
      "General",
      "Pediatrics",
      "ER",
      "OT",
      "ICU"
    ],
    "certifications": [
      "BLS"
    ],
    "experience_years": 2,
    "unavailability": [],
    "leave": {
      "annual": [],
      "sick": [],
      "maternity": []
    },
    "preferences": [
      "Evening"
    ],
    "contracted_hours": 40,
    "seniority_level": "Mid",
    "union_terms": [
      "max_45h_week",
      "1_rest_day"
    ]
  },
  {
    "nurse_id": "N011",
    "name": "Sophia Miller",
    "skills": [
      "General",
      "Pediatrics",
      "OT",
      "ICU"
    ],
    "certifications": [
      "BLS",
      "ENPC"
    ],
    "experience_years": 4,
    "unavailability": [],
    "leave": {
      "annual": [],
      "sick": [],
      "maternity": []
    },
    "preferences": [
      "Morning"
    ],
    "contracted_hours": 40,
    "seniority_level": "Mid",
    "union_terms": [
      "max_45h_week",
      "1_rest_day"
    ]
  },
  {
    "nurse_id": "N012",
    "name": "Chloe Rodriguez",
    "skills": [
      "General",
      "ER",
      "OT",
      "Pediatrics",
      "ICU"
    ],
    "certifications": [
      "BLS",
      "CEN",
      "ACLS"
    ],
    "experience_years": 9,
    "unavailability": [],
    "leave": {
      "annual": [],
      "sick": [],
      "maternity": []
    },
    "preferences": [
      "Night"
    ],
    "contracted_hours": 44,
    "seniority_level": "Senior",
    "union_terms": [
      "max_45h_week",
      "1_rest_day"
    ]
  },
  {
    "nurse_id": "N013",
    "name": "Mohammed Rodriguez",
    "skills": [
      "General",
      "Pediatrics",
      "ICU",
      "OT"
    ],
    "certifications": [
      "BLS"
    ],
    "experience_years": 1,
    "unavailability": [],
    "leave": {
      "annual": [],
      "sick": [],
      "maternity": []
    },
    "preferences": [
      "Night"
    ],
    "contracted_hours": 36,
    "seniority_level": "Junior",
    "union_terms": [
      "max_45h_week",
      "1_rest_day"
    ]
  },
  {
    "nurse_id": "N014",
    "name": "Catherine Wang",
    "skills": [
      "General",
      "ER",
      "Pediatrics",
      "OT",
      "ICU"
    ],
    "certifications": [
      "BLS",
      "PALS"
    ],
    "experience_years": 12,
    "unavailability": [],
    "leave": {
      "annual": [],
      "sick": [],
      "maternity": []
    },
    "preferences": [
      "Evening"
    ],
    "contracted_hours": 44,
    "seniority_level": "Senior",
    "union_terms": [
      "max_45h_week",
      "1_rest_day"
    ]
  },
  {
    "nurse_id": "N015",
    "name": "Lim Tan",
    "skills": [
      "General",
      "Pediatrics",
      "ICU",
      "OT",
      "ER"
    ],
    "certifications": [
      "BLS",
      "CEN"
    ],
    "experience_years": 2,
    "unavailability": [],
    "leave": {
      "annual": [],
      "sick": [],
      "maternity": []
    },
    "preferences": [
      "Evening"
    ],
    "contracted_hours": 40,
    "seniority_level": "Mid",
    "union_terms": [
      "max_45h_week",
      "1_rest_day"
    ]
  },
  {
    "nurse_id": "N016",
    "name": "Ethan Kim",
    "skills": [
      "ICU",
      "Pediatrics",
      "ER"
    ],
    "certifications": [
      "BLS",
      "CEN",
      "NRP"
    ],
    "experience_years": 0,
    "unavailability": [],
    "leave": {
      "annual": [],
      "sick": [],
      "maternity": []
    },
    "preferences": [
      "Morning"
    ],
    "contracted_hours": 36,
    "seniority_level": "Junior",
    "union_terms": [
      "max_45h_week",
      "1_rest_day"
    ]
  },
  {
    "nurse_id": "N017",
    "name": "Ryan Karim",
    "skills": [
      "ICU",
      "OT",
      "Pediatrics",
      "General",
      "ER"
    ],
    "certifications": [
      "BLS",
      "PALS"
    ],
    "experience_years": 11,
    "unavailability": [],
    "leave": {
      "annual": [],
      "sick": [],
      "maternity": []
    },
    "preferences": [
      "Night"
    ],
    "contracted_hours": 44,
    "seniority_level": "Senior",
    "union_terms": [
      "max_45h_week",
      "1_rest_day"
    ]
  },
  {
    "nurse_id": "N018",
    "name": "Victoria Wang",
    "skills": [
      "ICU",
      "ER",
      "General",
      "OT"
    ],
    "certifications": [
      "BLS",
      "ACLS",
      "ENPC"
    ],
    "experience_years": 13,
    "unavailability": [],
    "leave": {
      "annual": [],
      "sick": [],
      "maternity": []
    },
    "preferences": [
      "Night"
    ],
    "contracted_hours": 44,
    "seniority_level": "Senior",
    "union_terms": [
      "max_45h_week",
      "1_rest_day"
    ]
  },
  {
    "nurse_id": "N019",
    "name": "Lily Miller",
    "skills": [
      "ICU",
      "Pediatrics",
      "General",
      "OT",
      "ER"
    ],
    "certifications": [
      "BLS",
      "NRP",
      "ACLS"
    ],
    "experience_years": 3,
    "unavailability": [],
    "leave": {
      "annual": [],
      "sick": [],
      "maternity": []
    },
    "preferences": [
      "Evening"
    ],
    "contracted_hours": 40,
    "seniority_level": "Mid",
    "union_terms": [
      "max_45h_week",
      "1_rest_day"
    ]
  },
  {
    "nurse_id": "N020",
    "name": "Ava Hassan",
    "skills": [
      "ICU",
      "Pediatrics",
      "OT"
    ],
    "certifications": [
      "BLS",
      "NRP",
      "ACLS"
    ],
    "experience_years": 15,
    "unavailability": [],
    "leave": {
      "annual": [],
      "sick": [],
      "maternity": []
    },
    "preferences": [
      "Morning"
    ],
    "contracted_hours": 44,
    "seniority_level": "Senior",
    "union_terms": [
      "max_45h_week",
      "1_rest_day"
    ]
  },
  {
    "nurse_id": "N021",
    "name": "Jacob Patel",
    "skills": [
      "ICU",
      "ER",
      "Pediatrics"
    ],
    "certifications": [
      "BLS",
      "PALS"
    ],
    "experience_years": 4,
    "unavailability": [],
    "leave": {
      "annual": [],
      "sick": [],
      "maternity": []
    },
    "preferences": [
      "Night"
    ],
    "contracted_hours": 40,
    "seniority_level": "Mid",
    "union_terms": [
      "max_45h_week",
      "1_rest_day"
    ]
  },
  {
    "nurse_id": "N022",
    "name": "Lucas Singh",
    "skills": [
      "ICU",
      "General",
      "OT",
      "ER",
      "Pediatrics"
    ],
    "certifications": [
      "BLS",
      "ACLS"
    ],
    "experience_years": 10,
    "unavailability": [],
    "leave": {
      "annual": [],
      "sick": [],
      "maternity": []
    },
    "preferences": [
      "Morning"
    ],
    "contracted_hours": 44,
    "seniority_level": "Senior",
    "union_terms": [
      "max_45h_week",
      "1_rest_day"
    ]
  },
  {
    "nurse_id": "N023",
    "name": "Jacob Jackson",
    "skills": [
      "ICU",
      "Pediatrics",
      "General"
    ],
    "certifications": [
      "BLS"
    ],
    "experience_years": 15,
    "unavailability": [],
    "leave": {
      "annual": [],
      "sick": [],
      "maternity": []
    },
    "preferences": [
      "Night"
    ],
    "contracted_hours": 44,
    "seniority_level": "Senior",
    "union_terms": [
      "max_45h_week",
      "1_rest_day"
    ]
  },
  {
    "nurse_id": "N024",
    "name": "Grace Mahmood",
    "skills": [
      "ICU",
      "ER",
      "Pediatrics",
      "OT"
    ],
    "certifications": [
      "BLS"
    ],
    "experience_years": 5,
    "unavailability": [],
    "leave": {
      "annual": [],
      "sick": [],
      "maternity": []
    },
    "preferences": [
      "Night"
    ],
    "contracted_hours": 44,
    "seniority_level": "Senior",
    "union_terms": [
      "max_45h_week",
      "1_rest_day"
    ]
  },
  {
    "nurse_id": "N025",
    "name": "Jacob Johnson",
    "skills": [
      "ICU",
      "Pediatrics",
      "General",
      "ER"
    ],
    "certifications": [
      "BLS"
    ],
    "experience_years": 2,
    "unavailability": [],
    "leave": {
      "annual": [],
      "sick": [],
      "maternity": []
    },
    "preferences": [
      "Night"
    ],
    "contracted_hours": 40,
    "seniority_level": "Mid",
    "union_terms": [
      "max_45h_week",
      "1_rest_day"
    ]
  },
  {
    "nurse_id": "N026",
    "name": "Ryan Abdullah",
    "skills": [
      "ICU",
      "Pediatrics",
      "General",
      "ER"
    ],
    "certifications": [
      "BLS"
    ],
    "experience_years": 14,
    "unavailability": [],
    "leave": {
      "annual": [],
      "sick": [],
      "maternity": []
    },
    "preferences": [
      "Morning"
    ],
    "contracted_hours": 44,
    "seniority_level": "Senior",
    "union_terms": [
      "max_45h_week",
      "1_rest_day"
    ]
  },
  {
    "nurse_id": "N027",
    "name": "Emma Thompson",
    "skills": [
      "ICU",
      "Pediatrics",
      "General",
      "ER"
    ],
    "certifications": [
      "BLS"
    ],
    "experience_years": 5,
    "unavailability": [],
    "leave": {
      "annual": [],
      "sick": [],
      "maternity": []
    },
    "preferences": [
      "Night"
    ],
    "contracted_hours": 44,
    "seniority_level": "Senior",
    "union_terms": [
      "max_45h_week",
      "1_rest_day"
    ]
  },
  {
    "nurse_id": "N028",
    "name": "Maya Al-Zahra",
    "skills": [
      "ICU",
      "ER",
      "OT"
    ],
    "certifications": [
      "BLS",
      "CEN",
      "ACLS"
    ],
    "experience_years": 3,
    "unavailability": [],
    "leave": {
      "annual": [],
      "sick": [],
      "maternity": []
    },
    "preferences": [
      "Morning"
    ],
    "contracted_hours": 40,
    "seniority_level": "Mid",
    "union_terms": [
      "max_45h_week",
      "1_rest_day"
    ]
  },
  {
    "nurse_id": "N029",
    "name": "David Green",
    "skills": [
      "ICU",
      "OT",
      "General",
      "Pediatrics"
    ],
    "certifications": [
      "BLS"
    ],
    "experience_years": 8,
    "unavailability": [],
    "leave": {
      "annual": [],
      "sick": [],
      "maternity": []
    },
    "preferences": [
      "Morning"
    ],
    "contracted_hours": 44,
    "seniority_level": "Senior",
    "union_terms": [
      "max_45h_week",
      "1_rest_day"
    ]
  },
  {
    "nurse_id": "N030",
    "name": "Chloe Karim",
    "skills": [
      "ICU",
      "OT",
      "Pediatrics"
    ],
    "certifications": [
      "BLS"
    ],
    "experience_years": 15,
    "unavailability": [],
    "leave": {
      "annual": [],
      "sick": [],
      "maternity": []
    },
    "preferences": [
      "Night"
    ],
    "contracted_hours": 44,
    "seniority_level": "Senior",
    "union_terms": [
      "max_45h_week",
      "1_rest_day"
    ]
  },
  {
    "nurse_id": "N031",
    "name": "Ryan Green",
    "skills": [
      "ER",
      "OT",
      "ICU",
      "Pediatrics"
    ],
    "certifications": [
      "BLS",
      "CEN"
    ],
    "experience_years": 0,
    "unavailability": [],
    "leave": {
      "annual": [],
      "sick": [],
      "maternity": []
    },
    "preferences": [
      "Night"
    ],
    "contracted_hours": 36,
    "seniority_level": "Junior",
    "union_terms": [
      "max_45h_week",
      "1_rest_day"
    ]
  },
  {
    "nurse_id": "N032",
    "name": "Anita Osman",
    "skills": [
      "ER",
      "Pediatrics",
      "General",
      "ICU"
    ],
    "certifications": [
      "BLS",
      "CEN"
    ],
    "experience_years": 1,
    "unavailability": [],
    "leave": {
      "annual": [],
      "sick": [],
      "maternity": []
    },
    "preferences": [
      "Morning"
    ],
    "contracted_hours": 36,
    "seniority_level": "Junior",
    "union_terms": [
      "max_45h_week",
      "1_rest_day"
    ]
  },
  {
    "nurse_id": "N033",
    "name": "James Lee",
    "skills": [
      "ER",
      "General",
      "ICU",
      "OT"
    ],
    "certifications": [
      "BLS"
    ],
    "experience_years": 13,
    "unavailability": [],
    "leave": {
      "annual": [],
      "sick": [],
      "maternity": []
    },
    "preferences": [
      "Night"
    ],
    "contracted_hours": 44,
    "seniority_level": "Senior",
    "union_terms": [
      "max_45h_week",
      "1_rest_day"
    ]
  },
  {
    "nurse_id": "N034",
    "name": "Maria Clark",
    "skills": [
      "ER",
      "OT",
      "Pediatrics",
      "General"
    ],
    "certifications": [
      "BLS",
      "ENPC"
    ],
    "experience_years": 11,
    "unavailability": [],
    "leave": {
      "annual": [],
      "sick": [],
      "maternity": []
    },
    "preferences": [
      "Night"
    ],
    "contracted_hours": 44,
    "seniority_level": "Senior",
    "union_terms": [
      "max_45h_week",
      "1_rest_day"
    ]
  },
  {
    "nurse_id": "N035",
    "name": "Carlos Johnson",
    "skills": [
      "ER",
      "OT",
      "ICU",
      "Pediatrics",
      "General"
    ],
    "certifications": [
      "BLS"
    ],
    "experience_years": 14,
    "unavailability": [],
    "leave": {
      "annual": [],
      "sick": [],
      "maternity": []
    },
    "preferences": [
      "Evening"
    ],
    "contracted_hours": 44,
    "seniority_level": "Senior",
    "union_terms": [
      "max_45h_week",
      "1_rest_day"
    ]
  },
  {
    "nurse_id": "N036",
    "name": "Fatou O'Connor",
    "skills": [
      "ER",
      "OT",
      "General"
    ],
    "certifications": [
      "BLS",
      "PALS"
    ],
    "experience_years": 12,
    "unavailability": [],
    "leave": {
      "annual": [],
      "sick": [],
      "maternity": []
    },
    "preferences": [
      "Night"
    ],
    "contracted_hours": 44,
    "seniority_level": "Senior",
    "union_terms": [
      "max_45h_week",
      "1_rest_day"
    ]
  },
  {
    "nurse_id": "N037",
    "name": "Ryan Wang",
    "skills": [
      "ER",
      "Pediatrics",
      "ICU"
    ],
    "certifications": [
      "BLS",
      "ACLS",
      "ENPC"
    ],
    "experience_years": 10,
    "unavailability": [],
    "leave": {
      "annual": [],
      "sick": [],
      "maternity": []
    },
    "preferences": [
      "Night"
    ],
    "contracted_hours": 44,
    "seniority_level": "Senior",
    "union_terms": [
      "max_45h_week",
      "1_rest_day"
    ]
  },
  {
    "nurse_id": "N038",
    "name": "Isabella Rodriguez",
    "skills": [
      "ER",
      "OT",
      "General"
    ],
    "certifications": [
      "BLS",
      "NRP"
    ],
    "experience_years": 0,
    "unavailability": [],
    "leave": {
      "annual": [],
      "sick": [],
      "maternity": []
    },
    "preferences": [
      "Morning"
    ],
    "contracted_hours": 36,
    "seniority_level": "Junior",
    "union_terms": [
      "max_45h_week",
      "1_rest_day"
    ]
  },
  {
    "nurse_id": "N039",
    "name": "Mohammed Wang",
    "skills": [
      "ER",
      "Pediatrics",
      "General"
    ],
    "certifications": [
      "BLS",
      "ENPC"
    ],
    "experience_years": 15,
    "unavailability": [],
    "leave": {
      "annual": [],
      "sick": [],
      "maternity": []
    },
    "preferences": [
      "Evening"
    ],
    "contracted_hours": 44,
    "seniority_level": "Senior",
    "union_terms": [
      "max_45h_week",
      "1_rest_day"
    ]
  },
  {
    "nurse_id": "N040",
    "name": "Fatima Kim",
    "skills": [
      "ER",
      "General",
      "OT",
      "Pediatrics",
      "ICU"
    ],
    "certifications": [
      "BLS",
      "ENPC",
      "CEN"
    ],
    "experience_years": 9,
    "unavailability": [],
    "leave": {
      "annual": [],
      "sick": [],
      "maternity": []
    },
    "preferences": [
      "Morning"
    ],
    "contracted_hours": 44,
    "seniority_level": "Senior",
    "union_terms": [
      "max_45h_week",
      "1_rest_day"
    ]
  },
  {
    "nurse_id": "N041",
    "name": "Aaliyah Lee",
    "skills": [
      "ER",
      "Pediatrics",
      "OT",
      "ICU",
      "General"
    ],
    "certifications": [
      "BLS"
    ],
    "experience_years": 0,
    "unavailability": [],
    "leave": {
      "annual": [],
      "sick": [],
      "maternity": []
    },
    "preferences": [
      "Night"
    ],
    "contracted_hours": 36,
    "seniority_level": "Junior",
    "union_terms": [
      "max_45h_week",
      "1_rest_day"
    ]
  },
  {
    "nurse_id": "N042",
    "name": "Chloe Santos",
    "skills": [
      "ER",
      "Pediatrics",
      "General",
      "OT",
      "ICU"
    ],
    "certifications": [
      "BLS",
      "ENPC"
    ],
    "experience_years": 6,
    "unavailability": [],
    "leave": {
      "annual": [],
      "sick": [],
      "maternity": []
    },
    "preferences": [
      "Morning"
    ],
    "contracted_hours": 44,
    "seniority_level": "Senior",
    "union_terms": [
      "max_45h_week",
      "1_rest_day"
    ]
  },
  {
    "nurse_id": "N043",
    "name": "Mohammed Cooper",
    "skills": [
      "ER",
      "OT",
      "General",
      "ICU",
      "Pediatrics"
    ],
    "certifications": [
      "BLS"
    ],
    "experience_years": 9,
    "unavailability": [],
    "leave": {
      "annual": [],
      "sick": [],
      "maternity": []
    },
    "preferences": [
      "Night"
    ],
    "contracted_hours": 44,
    "seniority_level": "Senior",
    "union_terms": [
      "max_45h_week",
      "1_rest_day"
    ]
  },
  {
    "nurse_id": "N044",
    "name": "Ryan Cooper",
    "skills": [
      "ER",
      "ICU",
      "Pediatrics",
      "OT",
      "General"
    ],
    "certifications": [
      "BLS",
      "NRP"
    ],
    "experience_years": 13,
    "unavailability": [],
    "leave": {
      "annual": [],
      "sick": [],
      "maternity": []
    },
    "preferences": [
      "Morning"
    ],
    "contracted_hours": 44,
    "seniority_level": "Senior",
    "union_terms": [
      "max_45h_week",
      "1_rest_day"
    ]
  },
  {
    "nurse_id": "N045",
    "name": "Michael Osman",
    "skills": [
      "ER",
      "General",
      "ICU",
      "OT"
    ],
    "certifications": [
      "BLS",
      "PALS",
      "ACLS"
    ],
    "experience_years": 5,
    "unavailability": [],
    "leave": {
      "annual": [],
      "sick": [],
      "maternity": []
    },
    "preferences": [
      "Night"
    ],
    "contracted_hours": 44,
    "seniority_level": "Senior",
    "union_terms": [
      "max_45h_week",
      "1_rest_day"
    ]
  },
  {
    "nurse_id": "N046",
    "name": "Nathan Rodriguez",
    "skills": [
      "General",
      "ER",
      "ICU",
      "OT",
      "Pediatrics"
    ],
    "certifications": [
      "BLS",
      "PALS"
    ],
    "experience_years": 4,
    "unavailability": [],
    "leave": {
      "annual": [],
      "sick": [],
      "maternity": []
    },
    "preferences": [
      "Night"
    ],
    "contracted_hours": 40,
    "seniority_level": "Mid",
    "union_terms": [
      "max_45h_week",
      "1_rest_day"
    ]
  },
  {
    "nurse_id": "N047",
    "name": "Sarah Ali",
    "skills": [
      "ICU",
      "General",
      "OT",
      "Pediatrics"
    ],
    "certifications": [
      "BLS"
    ],
    "experience_years": 0,
    "unavailability": [],
    "leave": {
      "annual": [],
      "sick": [],
      "maternity": []
    },
    "preferences": [
      "Night"
    ],
    "contracted_hours": 36,
    "seniority_level": "Junior",
    "union_terms": [
      "max_45h_week",
      "1_rest_day"
    ]
  },
  {
    "nurse_id": "N048",
    "name": "Sophia Cooper",
    "skills": [
      "General",
      "Pediatrics",
      "OT"
    ],
    "certifications": [
      "BLS",
      "NRP"
    ],
    "experience_years": 5,
    "unavailability": [],
    "leave": {
      "annual": [],
      "sick": [],
      "maternity": []
    },
    "preferences": [
      "Morning"
    ],
    "contracted_hours": 44,
    "seniority_level": "Senior",
    "union_terms": [
      "max_45h_week",
      "1_rest_day"
    ]
  },
  {
    "nurse_id": "N049",
    "name": "Samuel Zhang",
    "skills": [
      "ER",
      "ICU",
      "General"
    ],
    "certifications": [
      "BLS",
      "ENPC"
    ],
    "experience_years": 14,
    "unavailability": [],
    "leave": {
      "annual": [],
      "sick": [],
      "maternity": []
    },
    "preferences": [
      "Night"
    ],
    "contracted_hours": 44,
    "seniority_level": "Senior",
    "union_terms": [
      "max_45h_week",
      "1_rest_day"
    ]
  },
  {
    "nurse_id": "N050",
    "name": "Kevin Osman",
    "skills": [
      "General",
      "ER",
      "ICU"
    ],
    "certifications": [
      "BLS",
      "ENPC"
    ],
    "experience_years": 5,
    "unavailability": [],
    "leave": {
      "annual": [],
      "sick": [],
      "maternity": []
    },
    "preferences": [
      "Evening"
    ],
    "contracted_hours": 44,
    "seniority_level": "Senior",
    "union_terms": [
      "max_45h_week",
      "1_rest_day"
    ]
  }
]